<?xml version="1.0" encoding="utf-8" ?>
<SubParties>
  <Culture name="Norse">
    <SubParty Name ="Light Calvary">
      <Character>14,Snow Ween Rider,Two</Character>
    </SubParty>
    <SubParty Name ="Pikemen">
      <Character>15,Wimpy Longaxer,Two</Character>
    </SubParty>
    <SubParty Name ="Shock Troops">
      <Character>14,Gotland Footman,One</Character>
    </SubParty>
    <SubParty Name ="Spearmen">
      <Character>12,Nordic Spearman,One</Character>
      <Character>16,Nordic Sergeant,One</Character>
    </SubParty>
    <SubParty Name ="Vikings">
      <Character>14,Raider,One</Character>
      <Character>16,Viking,One</Character>
    </SubParty>
  </Culture>
</SubParties>
