<?xml version="1.0" encoding="utf-8" ?>
<Cultures>
  <Culture name="Amazonian">
    <Character name ="Arms">
      <AttackSpriteIndex>8</AttackSpriteIndex>
      <ECharacterType>Critter</ECharacterType>
      <FlinchSpriteIndex>7</FlinchSpriteIndex>
      <Perks>
        <Perk>Scaly</Perk>
        <Perk>T_Rex_Bite</Perk>
      </Perks>
      <Stats>
        <Agility>320</Agility>
        <Constitution>420</Constitution>
        <Intelligence>400</Intelligence>
        <Might>620</Might>
        <Perception>400</Perception>
        <Resolve>380</Resolve>
      </Stats>
      <WeaponAbility>Bite</WeaponAbility>
    </Character>
    <Character name ="Beardedino">
      <AttackSpriteIndex>9</AttackSpriteIndex>
      <ECharacterType>Critter</ECharacterType>
      <FlinchSpriteIndex>7</FlinchSpriteIndex>
      <Perks>
        <Perk>Dino_Bite</Perk>
        <Perk>Scaly</Perk>
      </Perks>
      <Stats>
        <Agility>280</Agility>
        <Constitution>350</Constitution>
        <Intelligence>600</Intelligence>
        <Might>570</Might>
        <Perception>280</Perception>
        <Resolve>300</Resolve>
      </Stats>
      <WeaponAbility>Bite</WeaponAbility>
    </Character>
    <Character name ="Curizard">
      <AttackSpriteIndex>8</AttackSpriteIndex>
      <ECharacterType>Critter</ECharacterType>
      <FlinchSpriteIndex>7</FlinchSpriteIndex>
      <Perks>
        <Perk>Scaly</Perk>
      </Perks>
      <Stats>
        <Agility>320</Agility>
        <Constitution>200</Constitution>
        <Intelligence>680</Intelligence>
        <Might>420</Might>
        <Perception>350</Perception>
        <Resolve>550</Resolve>
      </Stats>
    </Character>
    <Character name ="Denture">
      <AttackSpriteIndex>8</AttackSpriteIndex>
      <ECharacterType>Critter</ECharacterType>
      <FlinchSpriteIndex>7</FlinchSpriteIndex>
      <Perk>Dino_Bite</Perk>
      <Perks>
        <Perk>Dino_Bite</Perk>
        <Perk>Scaly</Perk>
      </Perks>
      <Stats>
        <Agility>400</Agility>
        <Constitution>420</Constitution>
        <Intelligence>280</Intelligence>
        <Might>550</Might>
        <Perception>380</Perception>
        <Resolve>620</Resolve>
      </Stats>
      <WeaponAbility>Bite</WeaponAbility>
    </Character>
    <Character name ="Dino Knight">
      <Class>Knight,4</Class>
      <Class>Dino_Knight,4</Class>
      <ECharacterType>Humanoid</ECharacterType>
      <ERace>Lizardman</ERace>
      <Perks>
        <Perk>Bash_Buddy</Perk>
        <Perk>Hulk</Perk>
        <Perk>Iron_Hide</Perk>
        <Perk>Two_Handed_Expert</Perk>
      </Perks>
      <PotentialArmors>
        <Armors name="One">
          <Armor>0.75,Dino Scale Armor,Four</Armor>
          <Armor>0.25,Dino Scale Armor,Three</Armor>
        </Armors>
        <Helms name="One">
          <Helm>0.35,Dino Scale Helm,Four</Helm>
          <Helm>0.25,Dino Scale Helm,Three</Helm>
        </Helms>
      </PotentialArmors>
      <PotentialWeapons>
        <RWeapons name="One">
          <RWeapon>0.375,Dino Greataxe,Four</RWeapon>
          <RWeapon>0.125,Dino Greataxe,Three</RWeapon>
          <RWeapon>0.375,Dino Warhammer,Four</RWeapon>
          <RWeapon>0.125,Dino Warhammer,Three</RWeapon>
        </RWeapons>
      </PotentialWeapons>
      <Stats>
        <Agility>520</Agility>
        <Constitution>400</Constitution>
        <Intelligence>540</Intelligence>
        <Might>480</Might>
        <Perception>530</Perception>
        <Resolve>450</Resolve>
      </Stats>
    </Character>
    <Character name ="Dino Priest">
      <Class>Cleric,2</Class>
      <Class>Divine_Mind,2</Class>
      <Class>Psion,2</Class>
      <ECharacterType>Humanoid</ECharacterType>
      <ERace>Lizardman</ERace>
      <Perks>
      </Perks>
      <PotentialArmors>
        <Armors name="One">
          <Armor>0.75,Dino Regalia,Five</Armor>
          <Armor>0.25,Dino Regalia,Four</Armor>
        </Armors>
        <Helms name="One">
          <Helm>0.75,Dino Headdress,Five</Helm>
          <Helm>0.25,Dino Headdress,Four</Helm>
        </Helms>
      </PotentialArmors>
      <PotentialWeapons>
        <RWeapons name="One">
          <RWeapon>0.75,Dino Staff,Five</RWeapon>
          <RWeapon>0.25,Dino Staff,Four</RWeapon>
        </RWeapons>
      </PotentialWeapons>
      <Stats>
        <Agility>350</Agility>
        <Constitution>280</Constitution>
        <Intelligence>780</Intelligence>
        <Might>450</Might>
        <Perception>680</Perception>
        <Resolve>550</Resolve>
      </Stats>
    </Character>
    <Character name ="Dino Scaleman">
      <Class>Soldier,5</Class>
      <ECharacterType>Humanoid</ECharacterType>
      <ERace>Lizardman</ERace>
      <Perks>
        <Perk>Bastion</Perk>
        <Perk>Scaly</Perk>
        <Perk>Medium_Shield_Expert</Perk>
        <Perk>Shield_Brother</Perk>
        <Perk>Shield_Happy</Perk>
        <Perk>Shield_Pro</Perk>
      </Perks>
      <PotentialArmors>
        <Armors name="One">
          <Armor>0.75,Dino Scale Armor,Four</Armor>
          <Armor>0.25,Dino Scale Armor,Three</Armor>
        </Armors>
        <Helms name="One">
          <Helm>0.75,Dino Scale Helm,Four</Helm>
          <Helm>0.25,Dino Scale Helm,Three</Helm>
        </Helms>
      </PotentialArmors>
      <PotentialWeapons>
        <LWeapons name="One">
          <LWeapon>0.75,Dino Shield,Four</LWeapon>
          <LWeapon>0.25,Dino Shield,Three</LWeapon>
        </LWeapons>
        <RWeapons name="One">
          <RWeapon>0.75,Dino Fang Club,Four</RWeapon>
          <RWeapon>0.25,Dino Fang Club,Three</RWeapon>
        </RWeapons>
      </PotentialWeapons>
      <Stats>
        <Agility>480</Agility>
        <Constitution>520</Constitution>
        <Intelligence>450</Intelligence>
        <Might>480</Might>
        <Perception>550</Perception>
        <Resolve>520</Resolve>
      </Stats>
    </Character>
    <Character name ="Dino Seraph">
      <Class>Cleric,5</Class>
      <Class>Divine_Mind,6</Class>
      <Class>Psion,5</Class>
      <ECharacterType>Humanoid</ECharacterType>
      <ERace>Lizardman</ERace>
      <Perks>
      </Perks>
      <PotentialArmors>
        <Armors name="One">
          <Armor>0.75,Dino Regalia,Three</Armor>
          <Armor>0.25,Dino Regalia,Two</Armor>
        </Armors>
        <Helms name="One">
          <Helm>0.75,Dino Headdress,Three</Helm>
          <Helm>0.25,Dino Headdress,Two</Helm>
        </Helms>
      </PotentialArmors>
      <PotentialWeapons>
        <RWeapons name="One">
          <RWeapon>0.75,Dino Staff,Four</RWeapon>
          <RWeapon>0.25,Dino Staff,Three</RWeapon>
        </RWeapons>
      </PotentialWeapons>
      <Stats>
        <Agility>350</Agility>
        <Constitution>280</Constitution>
        <Intelligence>780</Intelligence>
        <Might>450</Might>
        <Perception>680</Perception>
        <Resolve>550</Resolve>
      </Stats>
    </Character>
    <Character name ="Dino Squire">
      <Class>Knight,3</Class>
      <Class>Dino_Knight,1</Class>
      <ECharacterType>Humanoid</ECharacterType>
      <ERace>Lizardman</ERace>
      <Perks>
        <Perk>Hulk</Perk>
        <Perk>Iron_Hide</Perk>
        <Perk>Scaly</Perk>
      </Perks>
      <PotentialArmors>
        <Armors name="One">
          <Armor>0.75,Dino Scale Armor,Five</Armor>
          <Armor>0.25,Dino Scale Armor,Four</Armor>
        </Armors>
        <Helms name="One">
          <Helm>0.35,Dino Scale Helm,Five</Helm>
          <Helm>0.25,Dino Scale Helm,Four</Helm>
        </Helms>
      </PotentialArmors>
      <PotentialWeapons>
        <RWeapons name="One">
          <RWeapon>0.375,Dino Greataxe,Five</RWeapon>
          <RWeapon>0.125,Dino Greataxe,Four</RWeapon>
          <RWeapon>0.375,Dino Warhammer,Five</RWeapon>
          <RWeapon>0.125,Dino Warhammer,Four</RWeapon>
        </RWeapons>
      </PotentialWeapons>
      <Stats>
        <Agility>520</Agility>
        <Constitution>400</Constitution>
        <Intelligence>540</Intelligence>
        <Might>480</Might>
        <Perception>530</Perception>
        <Resolve>450</Resolve>
      </Stats>
    </Character>
    <Character name ="Divine Dino Priest">
      <Class>Cleric,3</Class>
      <Class>Divine_Mind,3</Class>
      <Class>Psion,3</Class>
      <ECharacterType>Humanoid</ECharacterType>
      <ERace>Lizardman</ERace>
      <Perks>
      </Perks>
      <PotentialArmors>
        <Armors name="One">
          <Armor>0.75,Dino Regalia,Four</Armor>
          <Armor>0.25,Dino Regalia,Three</Armor>
        </Armors>
        <Helms name="One">
          <Helm>0.75,Dino Headdress,Four</Helm>
          <Helm>0.25,Dino Headdress,Three</Helm>
        </Helms>
      </PotentialArmors>
      <PotentialWeapons>
        <RWeapons name="One">
          <RWeapon>0.75,Dino Staff,Four</RWeapon>
          <RWeapon>0.25,Dino Staff,Three</RWeapon>
        </RWeapons>
      </PotentialWeapons>
      <Stats>
        <Agility>350</Agility>
        <Constitution>280</Constitution>
        <Intelligence>780</Intelligence>
        <Might>450</Might>
        <Perception>680</Perception>
        <Resolve>550</Resolve>
      </Stats>
    </Character>
    <Character name ="Lizardman Militia">
      <Class>Warrior,1</Class>
      <ECharacterType>Humanoid</ECharacterType>
      <ERace>Lizardman</ERace>
      <Perks>
        <Perk>Scaly</Perk>
        <Perk>Shield_Happy</Perk>
      </Perks>
      <PotentialArmors>
      </PotentialArmors>
      <PotentialWeapons>
        <LWeapons name="One">
          <LWeapon>0.25,Dino Shield,Five</LWeapon>
          <LWeapon>0.10,Dino Shield,Four</LWeapon>
        </LWeapons>
        <RWeapons name="One">
          <RWeapon>0.75,Dino Fang Club,Five</RWeapon>
          <RWeapon>0.25,Dino Fang Club,Four</RWeapon>
        </RWeapons>
      </PotentialWeapons>
      <Stats>
        <Agility>450</Agility>
        <Constitution>550</Constitution>
        <Intelligence>350</Intelligence>
        <Might>570</Might>
        <Perception>420</Perception>
        <Resolve>380</Resolve>
      </Stats>
    </Character>
    <Character name ="Raptard">
      <AttackSpriteIndex>2</AttackSpriteIndex>
      <ECharacterType>Critter</ECharacterType>
      <FlinchSpriteIndex>1</FlinchSpriteIndex>
      <Perks>
        <Perk>Dino_Bite</Perk>
        <Perk>Scaly</Perk>
      </Perks>
      <Stats>
        <Agility>650</Agility>
        <Constitution>380</Constitution>
        <Intelligence>250</Intelligence>
        <Might>620</Might>
        <Perception>320</Perception>
        <Resolve>400</Resolve>
      </Stats>
      <WeaponAbility>Bite</WeaponAbility>
    </Character>
    <Character name ="Rawrasaur">
      <AttackSpriteIndex>8</AttackSpriteIndex>
      <ECharacterType>Critter</ECharacterType>
      <FlinchSpriteIndex>7</FlinchSpriteIndex>
      <Perks>
        <Perk>Scaly</Perk>
      </Perks>
      <Stats>
        <Agility>300</Agility>
        <Constitution>350</Constitution>
        <Intelligence>520</Intelligence>
        <Might>620</Might>
        <Perception>320</Perception>
        <Resolve>380</Resolve>
      </Stats>
    </Character>
    <Character name ="Raptard Rider">
      <Class>Warrior,3</Class>
      <ECharacterType>Humanoid</ECharacterType>
      <ERace>Lizardman</ERace>
      <Mount>Raptard</Mount>
      <Perks>
        <Perk>Scaly</Perk>
      </Perks>
      <PotentialArmors>
      </PotentialArmors>
      <PotentialWeapons>
        <LWeapons name="One">
          <LWeapon>0.25,Dino Shield,Five</LWeapon>
          <LWeapon>0.10,Dino Shield,Four</LWeapon>
        </LWeapons>
        <RWeapons name="One">
          <RWeapon>0.75,Dino Spear,Five</RWeapon>
          <RWeapon>0.25,Dino Spear,Four</RWeapon>
        </RWeapons>
      </PotentialWeapons>
      <Stats>
        <Agility>550</Agility>
        <Constitution>450</Constitution>
        <Intelligence>350</Intelligence>
        <Might>480</Might>
        <Perception>450</Perception>
        <Resolve>400</Resolve>
      </Stats>
    </Character>
    <Character name ="Solizard">
      <AttackSpriteIndex>8</AttackSpriteIndex>
      <ECharacterType>Critter</ECharacterType>
      <FlinchSpriteIndex>7</FlinchSpriteIndex>
      <Perks>
        <Perk>Scaly</Perk>
      </Perks>
      <Stats>
        <Agility>300</Agility>
        <Constitution>350</Constitution>
        <Intelligence>520</Intelligence>
        <Might>620</Might>
        <Perception>320</Perception>
        <Resolve>380</Resolve>
      </Stats>
    </Character>
    <Character name ="Tearex">
      <AttackSpriteIndex>24</AttackSpriteIndex>
      <ECharacterType>Critter</ECharacterType>
      <FlinchSpriteIndex>16</FlinchSpriteIndex>
      <Perks>
        <Perk>Scaly</Perk>
      </Perks>
      <Stats>
        <Agility>350</Agility>
        <Constitution>350</Constitution>
        <Intelligence>580</Intelligence>
        <Might>420</Might>
        <Perception>480</Perception>
        <Resolve>500</Resolve>
      </Stats>
    </Character>
    <Character name ="Thairex">
      <Abilities>
        <Ability name="Hadoken">
        </Ability>
        <Ability name ="Kamehameha">
        </Ability>
      </Abilities>
      <AttackSpriteIndex>1</AttackSpriteIndex>
      <ECharacterType>Critter</ECharacterType>
      <FlinchSpriteIndex>13</FlinchSpriteIndex>
      <Perks>
        <Perk>Scaly</Perk>
      </Perks>
      <Stats>
        <Agility>420</Agility>
        <Constitution>420</Constitution>
        <Intelligence>400</Intelligence>
        <Might>580</Might>
        <Perception>400</Perception>
        <Resolve>480</Resolve>
      </Stats>
      <WeaponAbility>Bite</WeaponAbility>
    </Character>
    <Character name="Tyrantaur">
      <AttackSpriteIndex>24</AttackSpriteIndex>
      <Abilities>
        <Ability name="Bite">
          <EEffect name="Megabite">
            <X>2.0</X>
            <Y>2.0</Y>
          </EEffect>
        </Ability>
      </Abilities>
      <ECharacterType>Critter</ECharacterType>
      <FlinchSpriteIndex>16</FlinchSpriteIndex>
      <Perks>
        <Perk>Gargantuan</Perk>
        <Perk>Iron_Hide</Perk>
        <Perk>Massive</Perk>
        <Perk>Scaly</Perk>
        <Perk>T_Rex_Bite</Perk>
      </Perks>
      <Stats>
        <Agility>400</Agility>
        <Constitution>820</Constitution>
        <Intelligence>320</Intelligence>
        <Might>850</Might>
        <Perception>350</Perception>
        <Resolve>650</Resolve>
      </Stats>
    </Character>
    <Character name ="Veteran Dino Knight">
      <Class>Knight,5</Class>
      <Class>Dino_Knight,7</Class>
      <ECharacterType>Humanoid</ECharacterType>
      <ERace>Lizardman</ERace>
      <Perks>
        <Perk>Bash_Buddy</Perk>
        <Perk>Hulk</Perk>
        <Perk>Iron_Hide</Perk>
        <Perk>Scaly</Perk>
        <Perk>Two_Handed_Expert</Perk>
      </Perks>
      <PotentialArmors>
        <Armors name="One">
          <Armor>0.75,Dino Scale Armor,Three</Armor>
          <Armor>0.25,Dino Scale Armor,Two</Armor>
        </Armors>
        <Helms name="One">
          <Helm>0.55,Dino Scale Helm,Three</Helm>
          <Helm>0.25,Dino Scale Helm,Two</Helm>
        </Helms>
      </PotentialArmors>
      <PotentialWeapons>
        <RWeapons name="One">
          <RWeapon>0.375,Dino Greataxe,Three</RWeapon>
          <RWeapon>0.125,Dino Greataxe,Two</RWeapon>
          <RWeapon>0.375,Dino Warhammer,Three</RWeapon>
          <RWeapon>0.125,Dino Warhammer,Two</RWeapon>
        </RWeapons>
      </PotentialWeapons>
      <Stats>
        <Agility>520</Agility>
        <Constitution>400</Constitution>
        <Intelligence>540</Intelligence>
        <Might>480</Might>
        <Perception>530</Perception>
        <Resolve>450</Resolve>
      </Stats>
    </Character>
  </Culture>
</Cultures>
